Workbook

Sheet Shared Core Registry
A1: ESG Shared Core — Canonical ID Registry · ~120 IDs · MVP Build List
A2: Domain | B2: Sub-Group | C2: Canonical ID (slug) | D2: Plain-language Label | E2: Data Type | F2: Unit | G2: CSRD | H2: CDP | I2: GRI | J2: IFRS S2 | K2: TCFD * | L2: SME Validation | M2: SME Owner | N2: Validation Date | O2: SME Notes / Comments | P2: Framework Notes
A3: Environment | B3: GHG — Scope 1 | C3: GHG_SCOPE1_TOTAL_tCO2e | D3: Total gross Scope 1 GHG emissions | E3: number | F3: tCO₂e | G3: ● | H3: ● | I3: ● | J3: ● | K3: ≡ | L3: Pending | P3: Core across all. ESRS E1-6, CDP C6.1, GRI 305-1, IFRS S2.29a
C4: GHG_SCOPE1_CO2_tCO2 | D4: Scope 1 — CO₂ emissions | E4: number | F4: tCO₂ | G4: ● | H4: ● | I4: ◌ | J4: ◌ | K4: ≡ | L4: Pending | P4: Gas-by-gas breakdown required in CSRD and CDP
C5: GHG_SCOPE1_CH4_tCO2e | D5: Scope 1 — CH₄ emissions | E5: number | F5: tCO₂e | G5: ● | H5: ● | I5: ◌ | J5: ◌ | K5: ≡ | L5: Pending | P5: Critical for oil & gas and agriculture sectors
C6: GHG_SCOPE1_N2O_tCO2e | D6: Scope 1 — N₂O emissions | E6: number | F6: tCO₂e | G6: ● | H6: ● | I6: ◌ | J6: ◌ | K6: ≡ | L6: Pending | P6: Agriculture, chemicals, waste sectors
C7: GHG_SCOPE1_BIOGENIC_tCO2 | D7: Scope 1 — biogenic CO₂ (gross) | E7: number | F7: tCO₂ | G7: ● | H7: ● | I7: ◌ | J7: ◌ | K7: ≡ | L7: Pending | P7: Reported separately from fossil GHG across all frameworks
C8: GHG_SCOPE1_METHODOLOGY | D8: Scope 1 calculation methodology | E8: select | F8: — | G8: ● | H8: ● | I8: ● | J8: ● | K8: ≡ | L8: Pending | P8: GHG Protocol Corporate Standard / ISO 14064 / sector-specific
C9: GHG_SCOPE1_BASE_YEAR | D9: Scope 1 base year for targets | E9: number | F9: YYYY | G9: ● | H9: ● | I9: ● | J9: ● | K9: ≡ | L9: Pending | P9: Required for target trajectory calculation
C10: GHG_SCOPE1_INTENSITY_tCO2e_MEUR | D10: Scope 1 carbon intensity (per €M revenue) | E10: number | F10: tCO₂e/M€ | G10: ● | H10: ● | I10: ◌ | J10: ● | K10: ≡ | L10: Pending | P10: Calculated: S1 total ÷ revenue. Express per unit output for industrial sectors
B11: GHG — Scope 2 | C11: GHG_SCOPE2_MARKET_tCO2e | D11: Scope 2 — market-based method | E11: number | F11: tCO₂e | G11: ● | H11: ● | I11: ● | J11: ● | K11: ≡ | L11: Pending | P11: Uses supplier emission factors / RECs / GOs. Both methods mandatory in CSRD and CDP
C12: GHG_SCOPE2_LOCATION_tCO2e | D12: Scope 2 — location-based method | E12: number | F12: tCO₂e | G12: ● | H12: ● | I12: ● | J12: ● | K12: ≡ | L12: Pending | P12: Uses national/regional grid emission factors. Two separate canonical IDs for Scope 2
C13: GHG_SCOPE2_RENEWABLE_PCT | D13: % electricity from renewable sources | E13: number | F13: % | G13: ● | H13: ● | I13: ● | J13: ◌ | K13: ≡ | L13: Pending | P13: Closely linked to S2 market method. Reported separately in ESRS E1 and CDP C8
C14: GHG_SCOPE2_ELEC_CONSUMED_MWh | D14: Total electricity consumed | E14: number | F14: MWh | G14: ● | H14: ● | I14: ● | J14: ● | K14: ≡ | L14: Pending | P14: Source data for Scope 2 calculation. Required in GRI 302-1
C15: GHG_SCOPE2_HEAT_STEAM_MWh | D15: Purchased heat, steam, cooling consumed | E15: number | F15: MWh | G15: ● | H15: ● | I15: ● | J15: ◌ | K15: ≡ | L15: Pending | P15: Separate from electricity in GRI 302-1 and ESRS E1
C16: GHG_SCOPE2_INTENSITY_tCO2e_MEUR | D16: Scope 2 carbon intensity (per €M revenue) | E16: number | F16: tCO₂e/M€ | G16: ● | H16: ● | I16: ◌ | J16: ● | K16: ≡ | L16: Pending | P16: Use market-based as primary, report both where required
B17: GHG — Scope 3 | C17: GHG_S3_CAT1_PURCHASED_tCO2e | D17: Scope 3 Cat.1 — Purchased goods & services | E17: number | F17: tCO₂e | G17: ● | H17: ● | I17: ● | J17: ● | K17: ≡ | L17: Pending | P17: Usually the largest S3 category. Supplier data or spend-based method
C18: GHG_S3_CAT2_CAPGOODS_tCO2e | D18: Scope 3 Cat.2 — Capital goods | E18: number | F18: tCO₂e | G18: ● | H18: ● | I18: ● | J18: ◌ | K18: ≡ | L18: Pending | P18: Equipment, machinery, buildings purchased during reporting year
C19: GHG_S3_CAT3_ENERGY_tCO2e | D19: Scope 3 Cat.3 — Fuel & energy-related activities | E19: number | F19: tCO₂e | G19: ● | H19: ● | I19: ● | J19: ◌ | K19: ≡ | L19: Pending | P19: Upstream extraction/production of fuels purchased. Not in S1 or S2
C20: GHG_S3_CAT4_TRANSPORT_UP_tCO2e | D20: Scope 3 Cat.4 — Upstream transportation | E20: number | F20: tCO₂e | G20: ● | H20: ● | I20: ● | J20: ◌ | K20: ≡ | L20: Pending | P20: Logistics from suppliers to the reporting company
C21: GHG_S3_CAT5_WASTE_tCO2e | D21: Scope 3 Cat.5 — Waste generated in operations | E21: number | F21: tCO₂e | G21: ● | H21: ● | I21: ● | J21: ◌ | K21: ≡ | L21: Pending | P21: Emissions from third-party waste disposal and treatment
C22: GHG_S3_CAT6_BIZ_TRAVEL_tCO2e | D22: Scope 3 Cat.6 — Business travel | E22: number | F22: tCO₂e | G22: ● | H22: ● | I22: ● | J22: ◌ | K22: ≡ | L22: Pending | P22: Flights, rail, hotels. Usually calculated from expense data
C23: GHG_S3_CAT7_COMMUTE_tCO2e | D23: Scope 3 Cat.7 — Employee commuting | E23: number | F23: tCO₂e | G23: ● | H23: ● | I23: ● | J23: ◌ | K23: ≡ | L23: Pending | P23: Typically via employee survey. Remote work days often included
C24: GHG_S3_CAT9_TRANSPORT_DOWN_tCO2e | D24: Scope 3 Cat.9 — Downstream transportation | E24: number | F24: tCO₂e | G24: ● | H24: ● | I24: ● | J24: ◌ | K24: ≡ | L24: Pending | P24: Logistics from company to end customer. Retailers and distributors
C25: GHG_S3_CAT11_USE_tCO2e | D25: Scope 3 Cat.11 — Use of sold products | E25: number | F25: tCO₂e | G25: ● | H25: ● | I25: ● | J25: ● | K25: ≡ | L25: Pending | P25: Dominant for automotive, appliances, electronics. Often 70–90% of total S3
C26: GHG_S3_CAT12_EOL_tCO2e | D26: Scope 3 Cat.12 — End-of-life treatment | E26: number | F26: tCO₂e | G26: ● | H26: ● | I26: ● | J26: ◌ | K26: ≡ | L26: Pending | P26: Waste disposal of sold products. Linked to E5 (circular economy)
C27: GHG_S3_CAT15_INVESTMENTS_tCO2e | D27: Scope 3 Cat.15 — Investments (financed emissions) | E27: number | F27: tCO₂e | G27: ● | H27: ● | I27: ◌ | J27: ● | K27: ≡ | L27: Pending | P27: Critical for financial institutions. Calculated via PCAF methodology
C28: GHG_S3_TOTAL_tCO2e | D28: Total Scope 3 emissions (all material categories) | E28: number | F28: tCO₂e | G28: ● | H28: ● | I28: ● | J28: ● | K28: ≡ | L28: Pending | P28: Sum of all reported categories. Materiality assessment determines included categories
C29: GHG_S3_CATEGORIES_EXCLUDED | D29: Scope 3 categories excluded + justification | E29: text | F29: — | G29: ● | H29: ● | I29: ● | J29: ● | K29: ≡ | L29: Pending | P29: All four frameworks require explanation of why categories were excluded
C30: GHG_S3_DATA_QUALITY_NOTE | D30: Scope 3 data quality & methodology note | E30: text | F30: — | G30: ● | H30: ● | I30: ◌ | J30: ● | K30: ≡ | L30: Pending | P30: Describes method used per category (measured / estimated / spend-based)
B31: Energy | C31: ENERGY_TOTAL_MWh | D31: Total energy consumption | E31: number | F31: MWh | G31: ● | H31: ● | I31: ● | J31: ● | K31: ≡ | L31: Pending | P31: GRI 302-1. Sum of all energy sources. Primary input for Scope 1 & 2
C32: ENERGY_FOSSIL_MWh | D32: Energy from fossil fuels | E32: number | F32: MWh | G32: ● | H32: ● | I32: ● | J32: ● | K32: ≡ | L32: Pending | P32: Fuel breakdown: natural gas, diesel, coal, etc.
C33: ENERGY_RENEWABLE_MWh | D33: Energy from renewable sources | E33: number | F33: MWh | G33: ● | H33: ● | I33: ● | J33: ● | K33: ≡ | L33: Pending | P33: Solar, wind, hydro, biomass (self-generated + purchased)
C34: ENERGY_INTENSITY_MWh_MEUR | D34: Energy intensity per €M revenue | E34: number | F34: MWh/M€ | G34: ● | H34: ● | I34: ● | J34: ◌ | K34: ≡ | L34: Pending | P34: GRI 302-3. Calculated field
C35: ENERGY_REDUCTION_MWh | D35: Energy savings from efficiency initiatives | E35: number | F35: MWh | G35: ● | H35: ● | I35: ● | J35: ◌ | K35: ≡ | L35: Pending | P35: GRI 302-4. Year-on-year energy reductions from specific projects
C36: ENERGY_TARGET_PCT_RENEWABLE | D36: Renewable energy target (%) | E36: number | F36: % | G36: ● | H36: ● | I36: ◌ | J36: ◌ | K36: ≡ | L36: Pending | P36: Target year + target % for renewable transition
C37: ENERGY_TARGET_REDUCTION_PCT | D37: Energy reduction target (% vs base year) | E37: number | F37: % | G37: ● | H37: ● | I37: ◌ | J37: ◌ | K37: ≡ | L37: Pending | P37: Often part of Science-Based Target or net-zero commitment
C38: ENERGY_INTERNAL_CARBON_PRICE | D38: Internal carbon price ($/tCO₂e) | E38: number | F38: $/tCO₂e | G38: ● | H38: ● | I38: ◌ | J38: ● | K38: ≡ | L38: Pending | P38: CDP C11 and IFRS S2. Shadow price used in investment decisions
B39: Water | C39: WATER_WITHDRAWAL_TOTAL_m3 | D39: Total water withdrawal | E39: number | F39: m³ | G39: ● | H39: ● | I39: ● | J39: ◌ | K39: ≡ | L39: Pending | P39: GRI 303-3. All sources: municipal, groundwater, surface, seawater
C40: WATER_STRESS_WITHDRAWAL_m3 | D40: Water withdrawal in water-stressed areas | E40: number | F40: m³ | G40: ● | H40: ● | I40: ● | J40: ◌ | K40: ≡ | L40: Pending | P40: Sites assessed via WRI Aqueduct or similar tool. Key risk indicator
C41: WATER_CONSUMPTION_TOTAL_m3 | D41: Total water consumption (withdrawn – discharged) | E41: number | F41: m³ | G41: ● | H41: ● | I41: ● | J41: ◌ | K41: ≡ | L41: Pending | P41: Net consumption after discharge. More meaningful than raw withdrawal
C42: WATER_DISCHARGE_TOTAL_m3 | D42: Total water discharge | E42: number | F42: m³ | G42: ● | H42: ◌ | I42: ● | J42: ◌ | K42: ≡ | L42: Pending | P42: GRI 303-4. Destination (sea, freshwater, third party)
C43: WATER_RECYCLED_PCT | D43: % of water recycled / reused | E43: number | F43: % | G43: ● | H43: ● | I43: ● | J43: ◌ | K43: ≡ | L43: Pending | P43: CDP W1. GRI 303-1. Efficiency indicator
C44: WATER_TARGET_REDUCTION_PCT | D44: Water withdrawal reduction target (% vs base year) | E44: number | F44: % | G44: ● | H44: ● | I44: ◌ | J44: ◌ | K44: ≡ | L44: Pending | P44: Includes target year and base year value
B45: Waste | C45: WASTE_TOTAL_GENERATED_t | D45: Total waste generated | E45: number | F45: tonnes | G45: ● | H45: ◌ | I45: ● | J45: ◌ | K45: ≡ | L45: Pending | P45: GRI 306-3. Hazardous + non-hazardous split required
C46: WASTE_HAZARDOUS_t | D46: Hazardous waste generated | E46: number | F46: tonnes | G46: ● | H46: ◌ | I46: ● | J46: ◌ | K46: ≡ | L46: Pending | P46: Regulatory definition varies by country. ESRS E2 overlap
C47: WASTE_DIVERTED_RECYCLED_t | D47: Waste diverted — recycling | E47: number | F47: tonnes | G47: ● | H47: ◌ | I47: ● | J47: ◌ | K47: ≡ | L47: Pending | P47: GRI 306-4. Key for circular economy claims (ESRS E5)
C48: WASTE_DIRECTED_LANDFILL_t | D48: Waste directed to landfill | E48: number | F48: tonnes | G48: ● | H48: ◌ | I48: ● | J48: ◌ | K48: ≡ | L48: Pending | P48: GRI 306-5. Most impactful disposal method for emissions
C49: WASTE_DIVERSION_RATE_PCT | D49: Waste diversion rate from landfill (%) | E49: number | F49: % | G49: ● | H49: ◌ | I49: ● | J49: ◌ | K49: ≡ | L49: Pending | P49: Calculated: (diverted / total) × 100. Common target metric
C50: WASTE_TARGET_REDUCTION_PCT | D50: Waste reduction target (% vs base year) | E50: number | F50: % | G50: ● | H50: ◌ | I50: ◌ | J50: ◌ | K50: ≡ | L50: Pending | P50: Often linked to circular economy strategy (ESRS E5)
B51: Climate Risk & Targets | C51: CLIMATE_NET_ZERO_TARGET_YEAR | D51: Net-zero commitment target year | E51: number | F51: YYYY | G51: ● | H51: ● | I51: ◌ | J51: ● | K51: ≡ | L51: Pending | P51: 2030 interim + 2050 long-term targets required in ESRS E1
C52: CLIMATE_SBTI_COMMITTED | D52: Science-Based Target committed (Y/N) | E52: boolean | F52: — | G52: ● | H52: ● | I52: ◌ | J52: ● | K52: ≡ | L52: Pending | P52: CDP C4.1b. High signal for investors. Links to target ambition level
C53: CLIMATE_GHG_REDUCTION_TARGET_PCT | D53: GHG reduction target (% vs base year) | E53: number | F53: % | G53: ● | H53: ● | I53: ● | J53: ● | K53: ≡ | L53: Pending | P53: Split by Scope 1+2 and Scope 3. Interim (2030) + long-term (2050)
C54: CLIMATE_SCENARIO_COVERAGE | D54: Scenario analysis conducted (Y/N + scenarios used) | E54: text | F54: — | G54: ● | H54: ● | I54: ◌ | J54: ● | K54: ≡ | L54: Pending | P54: IEA NZE, NGFS, RCP scenarios. 1.5°C-aligned scenario required
C55: CLIMATE_PHYSICAL_RISK_ACUTE_DESC | D55: Acute physical climate risks identified | E55: text | F55: — | G55: ● | H55: ● | I55: ◌ | J55: ● | K55: ≡ | L55: Pending | P55: Floods, wildfires, extreme heat events. Site-level where possible
C56: CLIMATE_PHYSICAL_RISK_CHRONIC_DESC | D56: Chronic physical climate risks identified | E56: text | F56: — | G56: ● | H56: ● | I56: ◌ | J56: ● | K56: ≡ | L56: Pending | P56: Sea-level rise, temperature trends, precipitation shifts
C57: CLIMATE_TRANSITION_RISK_DESC | D57: Transition risks identified (policy, tech, market) | E57: text | F57: — | G57: ● | H57: ● | I57: ◌ | J57: ● | K57: ≡ | L57: Pending | P57: Carbon price exposure, stranded asset risk, regulatory change
C58: CLIMATE_CAPEX_ALIGNED_PCT | D58: CapEx aligned to climate transition (%) | E58: number | F58: % | G58: ● | H58: ● | I58: ◌ | J58: ● | K58: ≡ | L58: Pending | P58: ESRS E1 Taxonomy alignment. % of CapEx in green/transition activities
A59: Social | B59: Workforce | C59: WFORCE_HEADCOUNT_TOTAL | D59: Total employees (headcount) | E59: number | F59: count | G59: ● | H59: ◌ | I59: ● | J59: ◌ | K59: ≡ | L59: Pending | P59: GRI 2-7. End of period headcount. Permanent + temporary split required
C60: WFORCE_FTE_TOTAL | D60: Total full-time equivalent (FTE) | E60: number | F60: FTE | G60: ● | H60: ◌ | I60: ● | J60: ◌ | K60: ≡ | L60: Pending | P60: ESRS S1-6. Normalised for part-time. Used for intensity metrics
C61: WFORCE_PERMANENT_PCT | D61: % employees on permanent contracts | E61: number | F61: % | G61: ● | H61: ◌ | I61: ● | J61: ◌ | K61: ≡ | L61: Pending | P61: Job security indicator. GRI 2-7c
C62: WFORCE_PARTTIME_PCT | D62: % employees part-time | E62: number | F62: % | G62: ● | H62: ◌ | I62: ● | J62: ◌ | K62: ≡ | L62: Pending | P62: GRI 2-7b. Working conditions indicator
C63: WFORCE_NEW_HIRES_COUNT | D63: New employee hires (count) | E63: number | F63: count | G63: ● | H63: ◌ | I63: ● | J63: ◌ | K63: ≡ | L63: Pending | P63: GRI 401-1. Split by age group and gender required
C64: WFORCE_TURNOVER_RATE_PCT | D64: Employee turnover rate (%) | E64: number | F64: % | G64: ● | H64: ◌ | I64: ● | J64: ◌ | K64: ≡ | L64: Pending | P64: GRI 401-1. Voluntary vs involuntary split valuable
C65: WFORCE_COLLECTIVE_BARGAIN_PCT | D65: % employees covered by collective bargaining | E65: number | F65: % | G65: ● | H65: ◌ | I65: ● | J65: ◌ | K65: ≡ | L65: Pending | P65: GRI 2-30. Freedom of association indicator
C66: WFORCE_TRAINING_HOURS_AVG | D66: Average training hours per employee per year | E66: number | F66: hours | G66: ● | H66: ◌ | I66: ● | J66: ◌ | K66: ≡ | L66: Pending | P66: GRI 404-1. Investment in human capital development
C67: WFORCE_PERF_REVIEW_PCT | D67: % employees receiving regular performance reviews | E67: number | F67: % | G67: ● | H67: ◌ | I67: ● | J67: ◌ | K67: ≡ | L67: Pending | P67: GRI 404-3. Career development indicator
C68: WFORCE_MEDIAN_WAGE_EUR | D68: Median employee base salary (€) | E68: number | F68: € | G68: ● | H68: ◌ | I68: ◌ | J68: ◌ | K68: ≡ | L68: Pending | P68: ESRS S1-16. Needed for CEO pay ratio. Split by gender
B69: Health & Safety | C69: OHS_FATALITIES_EMPLOYEES | D69: Work-related fatalities — employees | E69: number | F69: count | G69: ● | H69: ◌ | I69: ● | J69: ● | K69: ≡ | L69: Pending | P69: GRI 403-9. Zero is the only acceptable target. High investor scrutiny
C70: OHS_FATALITIES_CONTRACTORS | D70: Work-related fatalities — contractors | E70: number | F70: count | G70: ● | H70: ◌ | I70: ● | J70: ● | K70: ≡ | L70: Pending | P70: GRI 403-9. Must be reported separately from employees
C71: OHS_LTIR_EMPLOYEES | D71: Lost-time injury rate (LTIR) — employees | E71: number | F71: per 1M hrs | G71: ● | H71: ◌ | I71: ● | J71: ● | K71: ≡ | L71: Pending | P71: GRI 403-9. Industry benchmark standard
C72: OHS_LTIR_CONTRACTORS | D72: Lost-time injury rate (LTIR) — contractors | E72: number | F72: per 1M hrs | G72: ● | H72: ◌ | I72: ● | J72: ● | K72: ≡ | L72: Pending | P72: Separate tracking required by ESRS S1 and GRI 403
C73: OHS_RECORDABLE_RATE | D73: Total recordable incident rate (TRIR) | E73: number | F73: per 1M hrs | G73: ● | H73: ◌ | I73: ● | J73: ◌ | K73: ≡ | L73: Pending | P73: Broader than LTIR — includes recordable injuries without lost days
C74: OHS_DAYS_LOST | D74: Total days lost to work-related injuries | E74: number | F74: days | G74: ● | H74: ◌ | I74: ● | J74: ◌ | K74: ≡ | L74: Pending | P74: GRI 403-9. Total absenteeism from injury (not illness)
C75: OHS_WORK_HOURS_TOTAL | D75: Total hours worked (employees + contractors) | E75: number | F75: hours | G75: ● | H75: ◌ | I75: ● | J75: ● | K75: ≡ | L75: Pending | P75: Denominator for all rate calculations. Required by GRI 403-9
C76: OHS_MGMT_SYSTEM_PCT | D76: % workforce covered by OHS management system | E76: number | F76: % | G76: ● | H76: ◌ | I76: ● | J76: ◌ | K76: ≡ | L76: Pending | P76: GRI 403-8. ISO 45001 certification level if applicable
B77: Diversity & Equity | C77: DIV_GENDER_WOMEN_TOTAL_PCT | D77: % women in total workforce | E77: number | F77: % | G77: ● | H77: ◌ | I77: ● | J77: ◌ | K77: ≡ | L77: Pending | P77: GRI 405-1. Baseline metric for all gender reporting
C78: DIV_GENDER_WOMEN_MGMT_PCT | D78: % women in management / leadership roles | E78: number | F78: % | G78: ● | H78: ◌ | I78: ● | J78: ◌ | K78: ≡ | L78: Pending | P78: ESRS S1-15. Senior management + board split valuable
C79: DIV_GENDER_WOMEN_BOARD_PCT | D79: % women on board of directors | E79: number | F79: % | G79: ● | H79: ◌ | I79: ● | J79: ◌ | K79: ≡ | L79: Pending | P79: EU 40% target for large listed companies by 2026
C80: DIV_GENDER_PAY_GAP_PCT | D80: Gender pay gap (unadjusted, % difference) | E80: number | F80: % | G80: ● | H80: ◌ | I80: ● | J80: ◌ | K80: ≡ | L80: Pending | P80: ESRS S1-16. Median base salary gap women vs men
C81: DIV_CEO_PAY_RATIO | D81: CEO-to-median-employee pay ratio | E81: number | F81: ratio | G81: ● | H81: ◌ | I81: ● | J81: ◌ | K81: ≡ | L81: Pending | P81: ESRS S1-16. e.g. 45:1 means CEO earns 45× median employee
C82: DIV_AGE_UNDER30_PCT | D82: % employees under 30 years old | E82: number | F82: % | G82: ● | H82: ◌ | I82: ● | J82: ◌ | K82: ≡ | L82: Pending | P82: GRI 405-1. Age bracket: under 30, 30–50, over 50
C83: DIV_PARENTAL_LEAVE_RETURN_PCT | D83: Parental leave return-to-work rate (%) | E83: number | F83: % | G83: ● | H83: ◌ | I83: ● | J83: ◌ | K83: ≡ | L83: Pending | P83: GRI 401-3. Split by gender. Key retention indicator
C84: DIV_DISCRIMINATION_INCIDENTS | D84: Discrimination incidents reported (count) | E84: number | F84: count | G84: ● | H84: ◌ | I84: ● | J84: ◌ | K84: ≡ | L84: Pending | P84: GRI 406-1. Requires action taken / remediation status
C85: DIV_DISABILITY_PCT | D85: % employees with disabilities | E85: number | F85: % | G85: ● | H85: ◌ | I85: ◌ | J85: ◌ | K85: ≡ | L85: Pending | P85: ESRS S1-12. Self-disclosed. Increasingly required under CSRD
C86: DIV_SURVEY_ENGAGEMENT_SCORE | D86: Employee engagement / satisfaction score | E86: number | F86: score | G86: ● | H86: ◌ | I86: ◌ | J86: ◌ | K86: ≡ | L86: Pending | P86: ESRS S1-17. Survey-based. Scale and methodology must be disclosed
B87: Compensation | C87: COMP_LIVING_WAGE_PCT | D87: % employees earning above living wage | E87: number | F87: % | G87: ● | H87: ◌ | I87: ◌ | J87: ◌ | K87: ≡ | L87: Pending | P87: ESRS S1-10. Living wage varies by country. Anker methodology reference
C88: COMP_SOCIAL_PROTECTION_PCT | D88: % employees covered by social protection | E88: number | F88: % | G88: ● | H88: ◌ | I88: ◌ | J88: ◌ | K88: ≡ | L88: Pending | P88: ESRS S1-11. Health, unemployment, pension coverage
C89: COMP_ESG_EXEC_LINKED_PCT | D89: % executive compensation linked to ESG targets | E89: number | F89: % | G89: ● | H89: ● | I89: ● | J89: ● | K89: ≡ | L89: Pending | P89: CDP C1.3. High investor interest. % of variable pay tied to ESG KPIs
C90: COMP_GRIEVANCE_FILED | D90: Grievances filed by employees (count) | E90: number | F90: count | G90: ● | H90: ◌ | I90: ● | J90: ◌ | K90: ≡ | L90: Pending | P90: ESRS S1-20. Formal complaints. Requires resolution rate disclosure
C91: COMP_GRIEVANCE_RESOLVED_PCT | D91: % grievances resolved within reporting period | E91: number | F91: % | G91: ● | H91: ◌ | I91: ● | J91: ◌ | K91: ≡ | L91: Pending | P91: Paired with COMP_GRIEVANCE_FILED
C92: COMP_WHISTLEBLOWER_EXISTS | D92: Whistleblower mechanism in place (Y/N) | E92: boolean | F92: — | G92: ● | H92: ◌ | I92: ● | J92: ● | K92: ≡ | L92: Pending | P92: EU Whistleblower Protection Directive mandates this
C93: COMP_WHISTLEBLOWER_REPORTS | D93: Whistleblower reports received (count) | E93: number | F93: count | G93: ● | H93: ◌ | I93: ● | J93: ● | K93: ≡ | L93: Pending | P93: ESRS G1-3. Requires substantiation rate. Confidentiality note required
A94: Governance | B94: Governance | C94: GOV_BOARD_SIZE | D94: Total number of board members | E94: number | F94: count | G94: ● | H94: ● | I94: ● | J94: ● | K94: ≡ | L94: Pending | P94: GRI 2-9. Foundation for all board diversity metrics
C95: GOV_BOARD_INDEPENDENT_PCT | D95: % independent board members | E95: number | F95: % | G95: ● | H95: ● | I95: ● | J95: ● | K95: ≡ | L95: Pending | P95: GRI 2-9. Corporate governance best practice indicator
C96: GOV_BOARD_ESG_OVERSIGHT | D96: Board-level ESG oversight mechanism | E96: text | F96: — | G96: ● | H96: ● | I96: ● | J96: ● | K96: ≡ | L96: Pending | P96: Committee structure, frequency of ESG review. TCFD Pillar 1
C97: GOV_BOARD_ESG_TRAINING_PCT | D97: % board members with ESG/sustainability training | E97: number | F97: % | G97: ● | H97: ● | I97: ◌ | J97: ● | K97: ≡ | L97: Pending | P97: Competency requirement in ESRS 2 and CDP C1.1b
C98: GOV_ANTICORRUPT_TRAINING_PCT | D98: % employees trained on anti-corruption policies | E98: number | F98: % | G98: ● | H98: ◌ | I98: ● | J98: ● | K98: ≡ | L98: Pending | P98: GRI 205-2. Split by employee category and governance body
C99: GOV_CORRUPTION_INCIDENTS | D99: Confirmed corruption incidents (count) | E99: number | F99: count | G99: ● | H99: ◌ | I99: ● | J99: ● | K99: ≡ | L99: Pending | P99: GRI 205-3. Requires action taken disclosure
C100: GOV_LEGAL_FINES_EUR | D100: Total significant fines for non-compliance (€) | E100: number | F100: € | G100: ● | H100: ◌ | I100: ● | J100: ◌ | K100: ≡ | L100: Pending | P100: GRI 2-27. Legal compliance signal. All fine categories
...

Sheet Legend & Instructions
A1: Legend & Instructions — Shared Core Canonical ID Registry
A3: Framework Coverage Dots
A4: Column | B4: Symbol | C4: Meaning
A5: CSRD / CDP / GRI / IFRS S2 | B5: ● (filled) | C5: Mandatory or standard requirement in this framework
A6: CSRD / CDP / GRI / IFRS S2 | B6: ◌ (faded) | C6: Conditional — required only if material or sector-specific
A7: TCFD | B7: ≡ | C7: Fully covered by CSRD E1 + IFRS S2 — no net new IDs needed
A9: Domain Color Coding
A10: E | B10: Environment
A11: S | B11: Social
A12: G | B12: Governance
A13: X | B13: Cross-cutting
A15: SME Validation Column — Instructions
A16: Pending | B16: Default status for all IDs. Awaiting SME review.
A17: In Review | B17: SME is actively reviewing this canonical ID and its framework mappings.
A18: Approved | B18: SME has confirmed the ID, label, type, unit, and framework coverage are correct.
A19: Flagged | B19: SME has identified an issue. Use the SME Notes column to describe the problem.
A21: Column Definitions
A22: Canonical ID (slug) | B22: Unique identifier for the data point. Framework-agnostic. Follows DOMAIN_CONCEPT_UNIT pattern.
A23: Plain-language Label | B23: Human-readable name shown to users in the product UI. No framework jargon.
A24: Data Type | B24: number / text / boolean / select. Determines the DataSource column type generated.
A25: Unit | B25: Measurement unit (tCO₂e, MWh, %, count, €, etc.). Stored as metadata on the canonical_requirement table.
A26: CSRD / CDP / GRI / IFRS | B26: ● = mandatory or standard in this framework. ◌ = conditional or sector-specific.
A27: TCFD | B27: ≡ = fully covered by CSRD E1 and IFRS S2. No dedicated TCFD-only canonical IDs are needed.
A28: SME Validation | B28: Dropdown: Pending / In Review / Approved / Flagged. Use to track review progress by domain.
A29: SME Owner | B29: Name or initials of the subject matter expert responsible for validating this ID.
A30: Validation Date | B30: Date format YYYY-MM-DD. Fill when status changes to Approved or Flagged.
A31: SME Notes / Comments | B31: Free-text field for SME observations, questions, edge cases, or flagged issues.
A32: Framework Notes | B32: Technical notes on methodology, GRI/ESRS references, and calculation rules. Pre-filled by product team.

Sheet Validation Tracker
A1: SME Validation Tracker — Status summary pulled from Registry sheet
A2: Domain | B2: Sub-Group | C2: Canonical ID | D2: SME Owner | E2: Status | F2: Validation Date | G2: Notes
A3: ='Shared Core Registry'!A3 -> Environment | B3: ='Shared Core Registry'!B3 -> GHG — Scope 1 | C3: ='Shared Core Registry'!C3 -> GHG_SCOPE1_TOTAL_tCO2e | D3: ='Shared Core Registry'!M3 -> 0 | E3: ='Shared Core Registry'!L3 -> Pending | F3: ='Shared Core Registry'!N3 -> 0 | G3: ='Shared Core Registry'!O3 -> 0
A4: ='Shared Core Registry'!A4 -> 0 | B4: ='Shared Core Registry'!B4 -> 0 | C4: ='Shared Core Registry'!C4 -> GHG_SCOPE1_CO2_tCO2 | D4: ='Shared Core Registry'!M4 -> 0 | E4: ='Shared Core Registry'!L4 -> Pending | F4: ='Shared Core Registry'!N4 -> 0 | G4: ='Shared Core Registry'!O4 -> 0
A5: ='Shared Core Registry'!A5 -> 0 | B5: ='Shared Core Registry'!B5 -> 0 | C5: ='Shared Core Registry'!C5 -> GHG_SCOPE1_CH4_tCO2e | D5: ='Shared Core Registry'!M5 -> 0 | E5: ='Shared Core Registry'!L5 -> Pending | F5: ='Shared Core Registry'!N5 -> 0 | G5: ='Shared Core Registry'!O5 -> 0
A6: ='Shared Core Registry'!A6 -> 0 | B6: ='Shared Core Registry'!B6 -> 0 | C6: ='Shared Core Registry'!C6 -> GHG_SCOPE1_N2O_tCO2e | D6: ='Shared Core Registry'!M6 -> 0 | E6: ='Shared Core Registry'!L6 -> Pending | F6: ='Shared Core Registry'!N6 -> 0 | G6: ='Shared Core Registry'!O6 -> 0
A7: ='Shared Core Registry'!A7 -> 0 | B7: ='Shared Core Registry'!B7 -> 0 | C7: ='Shared Core Registry'!C7 -> GHG_SCOPE1_BIOGENIC_tCO2 | D7: ='Shared Core Registry'!M7 -> 0 | E7: ='Shared Core Registry'!L7 -> Pending | F7: ='Shared Core Registry'!N7 -> 0 | G7: ='Shared Core Registry'!O7 -> 0
A8: ='Shared Core Registry'!A8 -> 0 | B8: ='Shared Core Registry'!B8 -> 0 | C8: ='Shared Core Registry'!C8 -> GHG_SCOPE1_METHODOLOGY | D8: ='Shared Core Registry'!M8 -> 0 | E8: ='Shared Core Registry'!L8 -> Pending | F8: ='Shared Core Registry'!N8 -> 0 | G8: ='Shared Core Registry'!O8 -> 0
A9: ='Shared Core Registry'!A9 -> 0 | B9: ='Shared Core Registry'!B9 -> 0 | C9: ='Shared Core Registry'!C9 -> GHG_SCOPE1_BASE_YEAR | D9: ='Shared Core Registry'!M9 -> 0 | E9: ='Shared Core Registry'!L9 -> Pending | F9: ='Shared Core Registry'!N9 -> 0 | G9: ='Shared Core Registry'!O9 -> 0
A10: ='Shared Core Registry'!A10 -> 0 | B10: ='Shared Core Registry'!B10 -> 0 | C10: ='Shared Core Registry'!C10 -> GHG_SCOPE1_INTENSITY_tCO2e_MEUR | D10: ='Shared Core Registry'!M10 -> 0 | E10: ='Shared Core Registry'!L10 -> Pending | F10: ='Shared Core Registry'!N10 -> 0 | G10: ='Shared Core Registry'!O10 -> 0
A11: ='Shared Core Registry'!A11 -> 0 | B11: ='Shared Core Registry'!B11 -> GHG — Scope 2 | C11: ='Shared Core Registry'!C11 -> GHG_SCOPE2_MARKET_tCO2e | D11: ='Shared Core Registry'!M11 -> 0 | E11: ='Shared Core Registry'!L11 -> Pending | F11: ='Shared Core Registry'!N11 -> 0 | G11: ='Shared Core Registry'!O11 -> 0
A12: ='Shared Core Registry'!A12 -> 0 | B12: ='Shared Core Registry'!B12 -> 0 | C12: ='Shared Core Registry'!C12 -> GHG_SCOPE2_LOCATION_tCO2e | D12: ='Shared Core Registry'!M12 -> 0 | E12: ='Shared Core Registry'!L12 -> Pending | F12: ='Shared Core Registry'!N12 -> 0 | G12: ='Shared Core Registry'!O12 -> 0
A13: ='Shared Core Registry'!A13 -> 0 | B13: ='Shared Core Registry'!B13 -> 0 | C13: ='Shared Core Registry'!C13 -> GHG_SCOPE2_RENEWABLE_PCT | D13: ='Shared Core Registry'!M13 -> 0 | E13: ='Shared Core Registry'!L13 -> Pending | F13: ='Shared Core Registry'!N13 -> 0 | G13: ='Shared Core Registry'!O13 -> 0
A14: ='Shared Core Registry'!A14 -> 0 | B14: ='Shared Core Registry'!B14 -> 0 | C14: ='Shared Core Registry'!C14 -> GHG_SCOPE2_ELEC_CONSUMED_MWh | D14: ='Shared Core Registry'!M14 -> 0 | E14: ='Shared Core Registry'!L14 -> Pending | F14: ='Shared Core Registry'!N14 -> 0 | G14: ='Shared Core Registry'!O14 -> 0
... A113: ='Shared Core Registry'!A113 -> 0 | B113: ='Shared Core Registry'!B113 -> 0 | C113: ='Shared Core Registry'!C113 -> META_FRAMEWORKS_APPLIED | D113: ='Shared Core Registry'!M113 -> 0 | E113: ='Shared Core Registry'!L113 -> Pending | F113: ='Shared Core Registry'!N113 -> 0 | G113: ='Shared Core Registry'!O113 -> 0
A116: Validation Progress Summary
A117: Total IDs | E117: =COUNTA(C3:C113) -> 111
A118: Approved | E118: =COUNTIF(E3:E113,"Approved") -> 0
A119: In Review | E119: =COUNTIF(E3:E113,"In Review") -> 0
A120: Flagged | E120: =COUNTIF(E3:E113,"Flagged") -> 0
A121: Pending | E121: =COUNTIF(E3:E113,"Pending") -> 111
A122: % Complete | E122: =IFERROR(COUNTIF(E3:E113,"Approved")/COUNTA(E3:E113),0) -> 0
